jitproxy/__init__.py
jitproxy/jitproxy.py
jitproxy-1.1.0.dist-info/LICENSE
jitproxy-1.1.0.dist-info/WHEEL
jitproxy-1.1.0.dist-info/METADATA
jitproxy-1.1.0.dist-info/RECORD
